czudf_toolkit/__init__.py
czudf_toolkit/_annotate.py
czudf_toolkit/_version.py
czudf_toolkit-0.0.1.dev0.dist-info/METADATA
czudf_toolkit-0.0.1.dev0.dist-info/WHEEL
czudf_toolkit-0.0.1.dev0.dist-info/licenses/LICENSE
czudf_toolkit-0.0.1.dev0.dist-info/RECORD
