Metadata-Version: 2.4
Name: czudf-toolkit
Version: 0.0.1.dev0
Summary: Python toolkit for developing UDFs on the ClickZetta platform
Project-URL: Homepage, https://github.com/czudf/czudf-python-toolkit
Project-URL: Repository, https://github.com/czudf/czudf-python-toolkit
Project-URL: Issues, https://github.com/czudf/czudf-python-toolkit/issues
Author-email: "guantao.gao" <guantao.gao@clickzetta.com>
License-File: LICENSE
Classifier: Development Status :: 3 - Alpha
Classifier: Intended Audience :: Developers
Classifier: License :: OSI Approved :: Apache Software License
Classifier: Operating System :: OS Independent
Classifier: Programming Language :: Python :: 3
Classifier: Programming Language :: Python :: 3 :: Only
Classifier: Programming Language :: Python :: 3.10
Classifier: Programming Language :: Python :: 3.11
Classifier: Programming Language :: Python :: 3.12
Classifier: Programming Language :: Python :: 3.13
Classifier: Topic :: Software Development :: Libraries :: Python Modules
Requires-Python: >=3.10
